LICENSE
README.rst
protocon
setup.py
lib/protocon/__init__.py
lib/protocon/color.py
lib/protocon/connection_driver.py
lib/protocon/conversion.py
lib/protocon/engine.py
lib/protocon/errors.py
lib/protocon/plugin_manager.py
lib/protocon/utilities.py
lib/protocon.egg-info/PKG-INFO
lib/protocon.egg-info/SOURCES.txt
lib/protocon.egg-info/dependency_links.txt
lib/protocon.egg-info/requires.txt
lib/protocon.egg-info/top_level.txt
lib/protocon/plugins/__init__.py
lib/protocon/plugins/driver_ether.py
lib/protocon/plugins/driver_l2.py
lib/protocon/plugins/driver_null.py
lib/protocon/plugins/driver_serial.py
lib/protocon/plugins/driver_tcp.py
lib/protocon/plugins/driver_udp.py
lib/protocon/plugins/driver_unix.py