Metadata-Version: 2.1
Name: protocon
Version: 1.4.0
Summary: Protocon is a socket-centric framework for rapidly prototyping connections through simple send and receive transcripts.
Home-page: https://github.com/zeroSteiner/protocon
Author: Spencer McIntyre
Author-email: zeroSteiner@gmail.com
Maintainer: Spencer McIntyre
Maintainer-email: zeroSteiner@gmail.com
License: BSD
Classifier: Development Status :: 5 - Production/Stable
Classifier: Environment :: Console
Classifier: Intended Audience :: Developers
Classifier: Intended Audience :: Information Technology
Classifier: Intended Audience :: System Administrators
Classifier: License :: OSI Approved :: BSD License
Classifier: Operating System :: OS Independent
Classifier: Programming Language :: Python :: 3.6
Classifier: Programming Language :: Python :: 3.7
Classifier: Programming Language :: Python :: 3.8
Classifier: Programming Language :: Python :: 3.9
Classifier: Programming Language :: Python :: 3.10
Classifier: Programming Language :: Python :: 3.11
Classifier: Topic :: Security
Classifier: Topic :: Software Development :: Libraries :: Python Modules
License-File: LICENSE
Requires-Dist: boltons>=17.1.0
Requires-Dist: cmd2==2.4.3
Requires-Dist: crcelk==1.3
Requires-Dist: hyperlink>=18.0.0
Requires-Dist: ipython>=6.2.1
Requires-Dist: pluginbase>=0.5
Requires-Dist: pyserial>=3.4
Requires-Dist: termcolor>=1.1.0
